bdtheme/__init__.py
bdtheme/src/__init__.py
bdtheme/src/curses_app.py
bdtheme/src/main.py
bdtheme/src/themes.py
bdtheme-1.3.22.dist-info/LICENSE
bdtheme-1.3.22.dist-info/METADATA
bdtheme-1.3.22.dist-info/WHEEL
bdtheme-1.3.22.dist-info/entry_points.txt
bdtheme-1.3.22.dist-info/top_level.txt
bdtheme-1.3.22.dist-info/RECORD
