Metadata-Version: 2.1
Name: bdtheme
Version: 1.3.22
Summary: Console BeautifulDiscord theme manager
Author: TheAmmiR
License: MIT
Requires-Python: >=3.8
License-File: LICENSE
Requires-Dist: bs4
Requires-Dist: requests
Requires-Dist: lxml
Requires-Dist: beaudis
Requires-Dist: windows-curses
